src/__init__.py
src/backporting_tool/__init__.py
src/backporting_tool/app.py
src/backporting_tool/google_diff_match_patch.py
backporting-1.0.1.dist-info/METADATA
backporting-1.0.1.dist-info/WHEEL
backporting-1.0.1.dist-info/entry_points.txt
backporting-1.0.1.dist-info/top_level.txt
backporting-1.0.1.dist-info/zip-safe
backporting-1.0.1.dist-info/RECORD
