Metadata-Version: 2.1
Name: backporting
Version: 1.0.1
Summary: Backporting tool
Home-page: https://github.com/levon2111/backporting.git
Author: LY
Author-email: Levon Yeghiazaryan <levon2111@gmail.com>
License: MIT
Project-URL: Homepage, https://github.com/levon2111/backporting
Project-URL: Issues, https://github.com/levon2111/backporting/issues
Keywords: Backporting
Classifier: Programming Language :: Python :: 3
Classifier: License :: OSI Approved :: MIT License
Classifier: Operating System :: OS Independent
Requires-Python: >=3.8
